asterpy/__init__.py
asterpy/channel.py
asterpy/client.py
asterpy/connection_mode.py
asterpy/debug.py
asterpy/emoji.py
asterpy/error.py
asterpy/message.py
asterpy/server.py
asterpy/sync.py
asterpy/user.py
asterpy-0.5.0.dist-info/LICENSE
asterpy-0.5.0.dist-info/METADATA
asterpy-0.5.0.dist-info/WHEEL
asterpy-0.5.0.dist-info/top_level.txt
asterpy-0.5.0.dist-info/RECORD
