Metadata-Version: 2.1
Name: asterpy
Version: 0.5.0
Summary: A simple Python wrapper around the Aster protocol, inspired by the syntax of discord.py
Home-page: https://github.com/Jachdich/asterpy
Author: James Kitching
Author-email: jamesedkitching@gmail.com
Project-URL: Bug Tracker, https://github.com/Jachdich/asterpy/issues
Classifier: Programming Language :: Python :: 3
Classifier: License :: OSI Approved :: MIT License
Classifier: Operating System :: OS Independent
Requires-Python: >=3.8
License-File: LICENSE
